[
  {
    "line": 1,
    "elements": [
      {
        "before": [
          {
            "result": {
              "duration": 8143339801,
              "status": "passed"
            },
            "match": {
              "location": "LoginPageStepDefinition.before(Scenario)"
            }
          }
        ],
        "line": 4,
        "name": "Write a New Story",
        "description": "",
        "id": "automating-action-in-homepage;write-a-new-story",
        "after": [
          {
            "result": {
              "duration": 181870000,
              "status": "passed"
            },
            "match": {
              "location": "LoginPageStepDefinition.after(Scenario)"
            }
          }
        ],
        "type": "scenario",
        "keyword": "Scenario",
        "steps": [
          {
            "result": {
              "duration": 4568069000,
              "status": "passed"
            },
            "line": 6,
            "name": "User is in HomePage",
            "match": {
              "location": "HomePageStepDefinition.user_is_in_HomePage()"
            },
            "keyword": "Given "
          },
          {
            "result": {
              "duration": 4254609000,
              "status": "passed"
            },
            "line": 7,
            "name": "User clicks on WriteNewStory",
            "match": {
              "location": "HomePageStepDefinition.user_clicks_on_WriteNewStory()"
            },
            "keyword": "When "
          },
          {
            "result": {
              "duration": 17647799,
              "status": "passed"
            },
            "line": 8,
            "name": "Verify AddNewPost Page",
            "match": {
              "location": "NewStoryStepDefinition.verify_AddNewPost_Page()"
            },
            "keyword": "Then "
          },
          {
            "result": {
              "duration": 493990300,
              "status": "passed"
            },
            "line": 9,
            "name": "Enter Title and Paragraph",
            "match": {
              "location": "NewStoryStepDefinition.enter_Title_and_Paragraph()"
            },
            "keyword": "Then "
          },
          {
            "result": {
              "duration": 1322455700,
              "status": "passed"
            },
            "line": 10,
            "name": "Click on publish",
            "match": {
              "location": "NewStoryStepDefinition.click_on_publish()"
            },
            "keyword": "And "
          },
          {
            "result": {
              "duration": 848748301,
              "status": "passed"
            },
            "line": 11,
            "name": "Go Back to HomePage",
            "match": {
              "location": "NewStoryStepDefinition.go_Back_to_HomePage()"
            },
            "keyword": "And "
          },
          {
            "result": {
              "duration": 4811201,
              "status": "passed"
            },
            "line": 12,
            "name": "Verify HomePage",
            "match": {
              "location": "HomePageStepDefinition.verify_HomePage()"
            },
            "keyword": "And "
          }
        ],
        "tags": [
          {
            "line": 3,
            "name": "@SmokeTest"
          }
        ]
      }
    ],
    "name": "Automating Action in HomePage",
    "description": "",
    "id": "automating-action-in-homepage",
    "keyword": "Feature",
    "uri": "HomePage.feature"
  }
]